<annotation>
	<folder>apel</folder>
	<filename>apel_train (17).jpg</filename>
	<path>C:\CODING\skripsi\dataset\train\apel\apel_train (17).jpg</path>
	<source>
		<database>Unknown</database>
	</source>
	<size>
		<width>2290</width>
		<height>2290</height>
		<depth>3</depth>
	</size>
	<segmented>0</segmented>
	<object>
		<name>apel</name>
		<pose>Unspecified</pose>
		<truncated>0</truncated>
		<difficult>0</difficult>
		<bndbox>
			<xmin>317</xmin>
			<ymin>532</ymin>
			<xmax>1895</xmax>
			<ymax>2110</ymax>
		</bndbox>
	</object>
</annotation>
